{
  "entries": [
    {
      "rank": "1st",
      "player": "aWiseMoose",
      "score": "362,899",
      "Percent": "100%",
      "platform": "360"
    },
    {
      "rank": "2nd",
      "player": "KramRal",
      "score": "362,883",
      "Percent": "100%",
      "platform": "360"
    },
    {
      "rank": "3rd",
      "player": "elScarecrow",
      "score": "362,687",
      "Percent": "100%",
      "platform": "360"
    },
    {
      "rank": "3rd",
      "player": "emulador",
      "score": "362,687",
      "Percent": "100%",
      "platform": "360"
    },
    {
      "rank": "3rd",
      "player": "Ex3LTheRaPiD",
      "score": "362,687",
      "Percent": "100%",
      "platform": "360"
    },
    {
      "rank": "6th",
      "player": "CuddlesIsAwesome",
      "score": "362,483",
      "Percent": "100%",
      "platform": "Wii"
    },
    {
      "rank": "6th",
      "player": "Jilde",
      "score": "362,483",
      "Percent": "100%",
      "platform": "360"
    },
    {
      "rank": "8th",
      "player": "UndeadFil13QC",
      "score": "362,479",
      "Percent": "100%",
      "platform": "Wii"
    },
    {
      "rank": "9th",
      "player": "JoelD77",
      "score": "362,443",
      "Percent": "100%",
      "platform": "360"
    },
    {
      "rank": "10th",
      "player": "alexhaz64",
      "score": "362,287",
      "Percent": "100%",
      "platform": "360"
    },
    {
      "rank": "11th",
      "player": "Lol21",
      "score": "362,087",
      "Percent": "100%",
      "platform": "PS3"
    },
    {
      "rank": "12th",
      "player": "Lo7",
      "score": "362,079",
      "Percent": "100%",
      "platform": "360"
    },
    {
      "rank": "12th",
      "player": "oct4v30n",
      "score": "362,079",
      "Percent": "100%",
      "platform": "360"
    },
    {
      "rank": "12th",
      "player": "WaHevi",
      "score": "362,079",
      "Percent": "100%",
      "platform": "360"
    },
    {
      "rank": "12th",
      "player": "WHIR3D",
      "score": "362,079",
      "Percent": "100%",
      "platform": "Wii"
    },
    {
      "rank": "12th",
      "player": "flamingbullets",
      "score": "362,079",
      "Percent": "100%",
      "platform": "360"
    },
    {
      "rank": "12th",
      "player": "arvain",
      "score": "362,079",
      "Percent": "100%",
      "platform": "360"
    },
    {
      "rank": "18th",
      "player": "xbillax",
      "score": "362,059",
      "Percent": "100%",
      "platform": "360"
    },
    {
      "rank": "19th",
      "player": "Fug",
      "score": "362,047",
      "Percent": "100%",
      "platform": "PS2"
    },
    {
      "rank": "20th",
      "player": "Jleggy12",
      "score": "361,887",
      "Percent": "100%",
      "platform": "PS3"
    },
    {
      "rank": "21st",
      "player": "FingerQuick",
      "score": "361,879",
      "Percent": "100%",
      "platform": "360"
    },
    {
      "rank": "22nd",
      "player": "Sammy90",
      "score": "361,875",
      "Percent": "100%",
      "platform": "PS2"
    },
    {
      "rank": "23rd",
      "player": "CyanCrayon86948",
      "score": "361,859",
      "Percent": "100%",
      "platform": "360"
    },
    {
      "rank": "24th",
      "player": "dnelson05",
      "score": "361,847",
      "Percent": "100%",
      "platform": "PS2"
    },
    {
      "rank": "25th",
      "player": "Ho11yw00d312",
      "score": "361,811",
      "Percent": "100%",
      "platform": "360"
    },
    {
      "rank": "26th",
      "player": "ChadCasket",
      "score": "361,683",
      "Percent": "100%",
      "platform": "360"
    },
    {
      "rank": "27th",
      "player": "Nighthawk814",
      "score": "361,679",
      "Percent": "100%",
      "platform": "360"
    },
    {
      "rank": "28th",
      "player": "Piso",
      "score": "361,675",
      "Percent": "100%",
      "platform": "360"
    },
    {
      "rank": "29th",
      "player": "Mr.Scientist",
      "score": "361,659",
      "Percent": "100%",
      "platform": "360"
    },
    {
      "rank": "29th",
      "player": "MrOmyA",
      "score": "361,659",
      "Percent": "100%",
      "platform": "360"
    },
    {
      "rank": "29th",
      "player": "KinGod",
      "score": "361,659",
      "Percent": "100%",
      "platform": "360"
    },
    {
      "rank": "32nd",
      "player": "ShonSuperStar",
      "score": "361,579",
      "Percent": "100%",
      "platform": "360"
    },
    {
      "rank": "33rd",
      "player": "SlasherManEXE",
      "score": "361,495",
      "Percent": "100%",
      "platform": "PS2"
    },
    {
      "rank": "34th",
      "player": "chemmajr",
      "score": "361,483",
      "Percent": "100%",
      "platform": "360"
    },
    {
      "rank": "35th",
      "player": "LlamaYip",
      "score": "361,479",
      "Percent": "100%",
      "platform": "360"
    },
    {
      "rank": "35th",
      "player": "KilljoyRPMX",
      "score": "361,479",
      "Percent": "100%",
      "platform": "360"
    },
    {
      "rank": "37th",
      "player": "smokyprogg",
      "score": "361,475",
      "Percent": "100%",
      "platform": "360"
    },
    {
      "rank": "38th",
      "player": "ThunderShade",
      "score": "361,459",
      "Percent": "100%",
      "platform": "360"
    },
    {
      "rank": "39th",
      "player": "sleeperwave",
      "score": "361,411",
      "Percent": "100%",
      "platform": "360"
    },
    {
      "rank": "40th",
      "player": "sean2490",
      "score": "361,403",
      "Percent": "100%",
      "platform": "360"
    },
    {
      "rank": "41st",
      "player": "GP69",
      "score": "361,335",
      "Percent": "100%",
      "platform": "360"
    },
    {
      "rank": "42nd",
      "player": "Bj0rn",
      "score": "361,287",
      "Percent": "100%",
      "platform": "360"
    },
    {
      "rank": "43rd",
      "player": "Mercurial",
      "score": "361,259",
      "Percent": "100%",
      "platform": "PS3"
    },
    {
      "rank": "44th",
      "player": "jdamillio",
      "score": "361,247",
      "Percent": "100%",
      "platform": "360"
    },
    {
      "rank": "44th",
      "player": "ChanceOfOne344",
      "score": "361,247",
      "Percent": "100%",
      "platform": "PS2"
    },
    {
      "rank": "46th",
      "player": "NejiHyuuga777",
      "score": "361,227",
      "Percent": "100%",
      "platform": "Wii"
    },
    {
      "rank": "47th",
      "player": "Hiraven",
      "score": "361,211",
      "Percent": "100%",
      "platform": "360"
    },
    {
      "rank": "48th",
      "player": "82erkle",
      "score": "361,203",
      "Percent": "100%",
      "platform": "PS2"
    },
    {
      "rank": "49th",
      "player": "Bomberman5697",
      "score": "361,119",
      "Percent": "100%",
      "platform": "PS2"
    },
    {
      "rank": "50th",
      "player": "yksi-kaksi-kolme",
      "score": "361,083",
      "Percent": "100%",
      "platform": "Wii"
    }
  ]
}