{
  "entries": [
    {
      "rank": "1st",
      "player": "Kyl3Ruth",
      "score": "311,239",
      "Percent": "100%",
      "platform": "360"
    },
    {
      "rank": "2nd",
      "player": "aWiseMoose",
      "score": "311,019",
      "Percent": "100%",
      "platform": "360"
    },
    {
      "rank": "3rd",
      "player": "Pas26",
      "score": "311,015",
      "Percent": "100%",
      "platform": "360"
    },
    {
      "rank": "4th",
      "player": "ggamer25",
      "score": "311,003",
      "Percent": "100%",
      "platform": "360"
    },
    {
      "rank": "5th",
      "player": "Fug",
      "score": "310,659",
      "Percent": "100%",
      "platform": "360"
    },
    {
      "rank": "6th",
      "player": "APEthehippy",
      "score": "310,643",
      "Percent": "100%",
      "platform": "360"
    },
    {
      "rank": "7th",
      "player": "matheushero",
      "score": "310,639",
      "Percent": "100%",
      "platform": "360"
    },
    {
      "rank": "8th",
      "player": "ukog-monkey",
      "score": "310,631",
      "Percent": "100%",
      "platform": "360"
    },
    {
      "rank": "9th",
      "player": "FingerQuick",
      "score": "310,627",
      "Percent": "100%",
      "platform": "360"
    },
    {
      "rank": "10th",
      "player": "Mxtchell",
      "score": "310,611",
      "Percent": "100%",
      "platform": "360"
    },
    {
      "rank": "11th",
      "player": "LemonMeringue",
      "score": "310,523",
      "Percent": "100%",
      "platform": "360"
    },
    {
      "rank": "12th",
      "player": "jdamillio",
      "score": "310,459",
      "Percent": "100%",
      "platform": "360"
    },
    {
      "rank": "13th",
      "player": "CuddlesIsAwesome",
      "score": "310,455",
      "Percent": "100%",
      "platform": "360"
    },
    {
      "rank": "14th",
      "player": "marioluigi1994",
      "score": "310,447",
      "Percent": "100%",
      "platform": "360"
    },
    {
      "rank": "15th",
      "player": "Bones909",
      "score": "310,439",
      "Percent": "100%",
      "platform": "PS3"
    },
    {
      "rank": "16th",
      "player": "alexhaz64",
      "score": "310,415",
      "Percent": "100%",
      "platform": "360"
    },
    {
      "rank": "17th",
      "player": "Sammy90",
      "score": "310,403",
      "Percent": "100%",
      "platform": "Wii"
    },
    {
      "rank": "18th",
      "player": "B1sse",
      "score": "310,391",
      "Percent": "100%",
      "platform": "360"
    },
    {
      "rank": "19th",
      "player": "WaHevi",
      "score": "310,379",
      "Percent": "100%",
      "platform": "360"
    },
    {
      "rank": "20th",
      "player": "JoelD77",
      "score": "310,375",
      "Percent": "100%",
      "platform": "360"
    },
    {
      "rank": "21st",
      "player": "Lo7",
      "score": "310,371",
      "Percent": "100%",
      "platform": "360"
    },
    {
      "rank": "21st",
      "player": "sean2490",
      "score": "310,371",
      "Percent": "100%",
      "platform": "360"
    },
    {
      "rank": "21st",
      "player": "Jleggy12",
      "score": "310,371",
      "Percent": "100%",
      "platform": "PS3"
    },
    {
      "rank": "24th",
      "player": "UndeadFil13QC",
      "score": "310,343",
      "Percent": "100%",
      "platform": "Wii"
    },
    {
      "rank": "25th",
      "player": "chemmajr",
      "score": "310,311",
      "Percent": "100%",
      "platform": "360"
    },
    {
      "rank": "26th",
      "player": "BlakePlaysGH",
      "score": "310,303",
      "Percent": "100%",
      "platform": "PS3"
    },
    {
      "rank": "27th",
      "player": "acatisfinetoo",
      "score": "310,301",
      "Percent": "100%",
      "platform": "PS2"
    },
    {
      "rank": "29th",
      "player": "FDXCpinballwiz",
      "score": "310,259",
      "Percent": "100%",
      "platform": "PS2"
    },
    {
      "rank": "29th",
      "player": "KramRal",
      "score": "310,215",
      "Percent": "100%",
      "platform": "360"
    },
    {
      "rank": "31st",
      "player": "iamchris4life",
      "score": "310,115",
      "Percent": "100%",
      "platform": "360"
    },
    {
      "rank": "31st",
      "player": "Chupacabraz",
      "score": "310,087",
      "Percent": "100%",
      "platform": "PS3"
    },
    {
      "rank": "32nd",
      "player": "NickGio9",
      "score": "310,059",
      "Percent": "100%",
      "platform": "Wii"
    },
    {
      "rank": "34th",
      "player": "XKaPwnageX",
      "score": "309,976",
      "Percent": "100%",
      "platform": "360"
    },
    {
      "rank": "34th",
      "player": "Hicchan",
      "score": "309,947",
      "Percent": "100%",
      "platform": "360"
    },
    {
      "rank": "35th",
      "player": "Halfbeasty",
      "score": "309,919",
      "Percent": "100%",
      "platform": "360"
    },
    {
      "rank": "37th",
      "player": "cassiopak",
      "score": "309,915",
      "Percent": "100%",
      "platform": "360"
    },
    {
      "rank": "37th",
      "player": "nickyboy909",
      "score": "309,915",
      "Percent": "100%",
      "platform": "PS3"
    },
    {
      "rank": "39th",
      "player": "shinycow17",
      "score": "309,911",
      "Percent": "100%",
      "platform": "360"
    },
    {
      "rank": "39th",
      "player": "Jilde",
      "score": "309,907",
      "Percent": "100%",
      "platform": "360"
    },
    {
      "rank": "41st",
      "player": "imasupafreakyoSH",
      "score": "309,885",
      "Percent": "100%",
      "platform": "PS2"
    },
    {
      "rank": "40th",
      "player": "bglass11",
      "score": "309,885",
      "Percent": "100%",
      "platform": "PS2"
    },
    {
      "rank": "42nd",
      "player": "arvain",
      "score": "309,855",
      "Percent": "100%",
      "platform": "360"
    },
    {
      "rank": "44th",
      "player": "ryn2075",
      "score": "309,799",
      "Percent": "100%",
      "platform": "Wii"
    },
    {
      "rank": "44th",
      "player": "Jwm64",
      "score": "309,799",
      "Percent": "100%",
      "platform": "Wii"
    },
    {
      "rank": "46th",
      "player": "Pi-Chan",
      "score": "309,787",
      "Percent": "100%",
      "platform": "PS3"
    },
    {
      "rank": "47th",
      "player": "SaidinWoT",
      "score": "309,771",
      "Percent": "100%",
      "platform": "360"
    },
    {
      "rank": "47th",
      "player": "Micktrippy53",
      "score": "309,723",
      "Percent": "100%",
      "platform": "Wii"
    },
    {
      "rank": "49th",
      "player": "GTManiac",
      "score": "309,703",
      "Percent": "100%",
      "platform": "Wii"
    },
    {
      "rank": "50th",
      "player": "baseballkid7",
      "score": "309,631",
      "Percent": "100%",
      "platform": "360"
    },
    {
      "rank": "50th",
      "player": "yksi-kaksi-kolme",
      "score": "309,623",
      "Percent": "100%",
      "platform": "Wii"
    }
  ]
}